{
    "darwin": {
        "branch": "master",
        "description": "nix modules for darwin",
        "homepage": "https://github.com/LnL7/nix-darwin",
        "owner": "LnL7",
        "repo": "nix-darwin",
        "rev": "2fce9974b6ad197682189d4978d77d122cb0ca3f",
        "sha256": "1bjb0y5j2zy887mq66j50fspi4npvr6his5bbb1c3dfiaqwkfjpb",
        "type": "tarball",
        "url": "https://github.com/LnL7/nix-darwin/archive/2fce9974b6ad197682189d4978d77d122cb0ca3f.tar.gz",
        "url_template": "https://github.com/<owner>/<repo>/archive/<rev>.tar.gz"
    },
    "home-manager": {
        "branch": "release-20.03",
        "description": "Manage a user environment using Nix",
        "homepage": "",
        "owner": "rycee",
        "repo": "home-manager",
        "rev": "a378bccd609c159fa8d421233b9c5eae04f02042",
        "sha256": "1cfh0aj60qriadvn5xvsp24p1xr06g68m3pfvzwahv2bd2cg261r",
        "type": "tarball",
        "url": "https://github.com/rycee/home-manager/archive/a378bccd609c159fa8d421233b9c5eae04f02042.tar.gz",
        "url_template": "https://github.com/<owner>/<repo>/archive/<rev>.tar.gz"
    },
    "niv": {
        "branch": "master",
        "description": "Easy dependency management for Nix projects",
        "homepage": "https://github.com/nmattia/niv",
        "owner": "nmattia",
        "repo": "niv",
        "rev": "f73bf8d584148677b01859677a63191c31911eae",
        "sha256": "0jlmrx633jvqrqlyhlzpvdrnim128gc81q5psz2lpp2af8p8q9qs",
        "type": "tarball",
        "url": "https://github.com/nmattia/niv/archive/f73bf8d584148677b01859677a63191c31911eae.tar.gz",
        "url_template": "https://github.com/<owner>/<repo>/archive/<rev>.tar.gz"
    },
    "nixos-hardware": {
        "branch": "master",
        "description": "A collection of NixOS modules covering hardware quirks.",
        "homepage": "",
        "owner": "NixOS",
        "repo": "nixos-hardware",
        "rev": "4b129a0f711aea22c52ad8ff48a3126a1b32a988",
        "sha256": "1mb3f658dgnibjbax67zjapfbm59v4df83w3a8gij10fvb5bj0dc",
        "type": "tarball",
        "url": "https://github.com/NixOS/nixos-hardware/archive/4b129a0f711aea22c52ad8ff48a3126a1b32a988.tar.gz",
        "url_template": "https://github.com/<owner>/<repo>/archive/<rev>.tar.gz"
    },
    "nixpkgs": {
        "branch": "nixos-20.03",
        "description": "A read-only mirror of NixOS/nixpkgs tracking the released channels. Send issues and PRs to",
        "homepage": "https://github.com/NixOS/nixpkgs",
        "owner": "NixOS",
        "repo": "nixpkgs-channels",
        "rev": "82b5f87fcc710a99c47c5ffe441589807a8202af",
        "sha256": "0wz07gzapdj95h9gf0rdc2ywgd7fnaivnf4vhwyh5gx24dblg7q8",
        "type": "tarball",
        "url": "https://github.com/NixOS/nixpkgs-channels/archive/82b5f87fcc710a99c47c5ffe441589807a8202af.tar.gz",
        "url_template": "https://github.com/<owner>/<repo>/archive/<rev>.tar.gz"
    },
    "nixpkgs-darwin": {
        "branch": "nixpkgs-19.03-darwin",
        "description": "A read-only mirror of NixOS/nixpkgs tracking the released channels. Send issues and PRs to",
        "homepage": "https://github.com/NixOS/nixpkgs",
        "owner": "NixOS",
        "repo": "nixpkgs-channels",
        "rev": "e6fe2df74ff30df952f418453ad046cb0126df38",
        "sha256": "08k9xy7vchvm1xps4hmsik62l9xyqqpxvpv7rqvks2k0ldngjsh5",
        "type": "tarball",
        "url": "https://github.com/NixOS/nixpkgs-channels/archive/e6fe2df74ff30df952f418453ad046cb0126df38.tar.gz",
        "url_template": "https://github.com/<owner>/<repo>/archive/<rev>.tar.gz"
    },
    "nixpkgs-unstable": {
        "branch": "master",
        "description": "Nix Packages collection",
        "homepage": null,
        "owner": "NixOS",
        "repo": "nixpkgs",
        "rev": "698e71db2c47b5d3a206c65288f88ab4320eaf1e",
        "sha256": "1lwlxjb38mis83hfi6d4i8yrblb31zvk5ff5wx9csghbk2pki9w1",
        "type": "tarball",
        "url": "https://github.com/NixOS/nixpkgs/archive/698e71db2c47b5d3a206c65288f88ab4320eaf1e.tar.gz",
        "url_template": "https://github.com/<owner>/<repo>/archive/<rev>.tar.gz"
    },
    "nur": {
        "branch": "master",
        "description": "Nix User Repository: User contributed nix packages [maintainer=@Mic92]",
        "homepage": "https://github.com/nix-community/NUR",
        "owner": "nix-community",
        "repo": "NUR",
        "rev": "3be99891588b4a0354ed12f669909832fa9eb68d",
        "sha256": "1l3q0hp491iwnpazj04h8y106p39vdk24gnj94sjkd999q9dkrxy",
        "type": "tarball",
        "url": "https://github.com/nix-community/NUR/archive/3be99891588b4a0354ed12f669909832fa9eb68d.tar.gz",
        "url_template": "https://github.com/<owner>/<repo>/archive/<rev>.tar.gz"
    }
}
